nesovetyu_com/__init__.py
nesovetyu_com/nesovetyu_com.py
nesovetyu_com-0.1.0.dist-info/LICENSE
nesovetyu_com-0.1.0.dist-info/METADATA
nesovetyu_com-0.1.0.dist-info/WHEEL
nesovetyu_com-0.1.0.dist-info/top_level.txt
nesovetyu_com-0.1.0.dist-info/RECORD
