Metadata-Version: 2.1
Name: nesovetyu-com
Version: 0.1.0
Summary: nesovetyu_com
Home-page: https://github.com/NMelis/nesovetyu_com
Author: NMelis
Author-email: melis.zhoroev+scrubbers@gmail.com
License: MIT license
Keywords: nesovetyu_com
Platform: UNKNOWN
Classifier: Development Status :: 2 - Pre-Alpha
Classifier: Intended Audience :: Developers
Classifier: License :: OSI Approved :: MIT License
Classifier: Natural Language :: English
Classifier: Programming Language :: Python :: 2
Classifier: Programming Language :: Python :: 2.7
Classifier: Programming Language :: Python :: 3
Classifier: Programming Language :: Python :: 3.4
Classifier: Programming Language :: Python :: 3.5
Classifier: Programming Language :: Python :: 3.6
Classifier: Programming Language :: Python :: 3.7
Requires-Dist: requests
Requires-Dist: bs4
